spatialcorr/__init__.py
spatialcorr/load_data.py
spatialcorr/plot.py
spatialcorr/statistical_test.py
spatialcorr/utils.py
spatialcorr/wrappers.py
spatialcorr/datasets/GSM4284326_P10_ST_rep2.h5ad
spatialcorr-1.2.0.dist-info/.ipynb_checkpoints/PKG-INFO-checkpoint
spatialcorr-1.2.0.dist-info/.ipynb_checkpoints/SOURCES-checkpoint.txt
spatialcorr-1.2.0.dist-info/.ipynb_checkpoints/dependency_links-checkpoint.txt
spatialcorr-1.2.0.dist-info/.ipynb_checkpoints/top_level-checkpoint.txt
spatialcorr-1.2.0.dist-info/.ipynb_checkpoints/zip-safe-checkpoint
spatialcorr-1.2.0.dist-info/LICENSE
spatialcorr-1.2.0.dist-info/METADATA
spatialcorr-1.2.0.dist-info/WHEEL
spatialcorr-1.2.0.dist-info/top_level.txt
spatialcorr-1.2.0.dist-info/zip-safe
spatialcorr-1.2.0.dist-info/RECORD
